lexgo/__init__.py
lexgo/__main__.py
lexgo/cli.py
lexgo/config.py
lexgo/trie.py
lexgo/utils.py
lexgo/data/__init__.py
lexgo/data/de.txt
lexgo/data/en.txt
lexgo/data/es.txt
lexgo/data/fr.txt
lexgo/data/it.txt
lexgo/data/pt.txt
lexgo-1.1.dist-info/LICENSE
lexgo-1.1.dist-info/METADATA
lexgo-1.1.dist-info/WHEEL
lexgo-1.1.dist-info/entry_points.txt
lexgo-1.1.dist-info/top_level.txt
lexgo-1.1.dist-info/RECORD
