Metadata-Version: 2.1
Name: lexgo
Version: 1.1
Summary: A lexicon search tool for language teachers and students. Explore word patterns in any language. 
Author: Joshua Kilpatrick
License: Apache-2.0
Project-URL: Homepage, https://github.com/joshkil/lexgo
Project-URL: Changelog, https://github.com/joshkil/lexgo/releases
Project-URL: Issues, https://github.com/joshkil/lexgo/issues
Project-URL: CI, https://github.com/joshkil/lexgo/actions
Classifier: License :: OSI Approved :: Apache Software License
Requires-Python: >=3.8
License-File: LICENSE
Requires-Dist: click
Provides-Extra: test
Requires-Dist: pytest; extra == "test"
